onefile/__init__.py
onefile/junit.py
onefile/report_html.py
onefile/template.html
onefile-0.1.2.dist-info/LICENSE
onefile-0.1.2.dist-info/METADATA
onefile-0.1.2.dist-info/WHEEL
onefile-0.1.2.dist-info/RECORD
